setup.py
yama/__init__.py
yama/cli.py
yama.egg-info/PKG-INFO
yama.egg-info/SOURCES.txt
yama.egg-info/dependency_links.txt
yama.egg-info/entry_points.txt
yama.egg-info/requires.txt
yama.egg-info/top_level.txt