Metadata-Version: 1.0
Name: yama
Version: 0.0.1
Summary: simple process monitoring
Home-page: https://github.com/ftzeng/yama
Author: Francis Tseng (@frnsys)
Author-email: UNKNOWN
License: MIT
Platform: UNKNOWN
